idaes_flowsheet_processor/__init__.py
idaes_flowsheet_processor/api.py
idaes_flowsheet_processor/conftest.py
idaes_flowsheet_processor/util.py
idaes_flowsheet_processor/_testing/README.md
idaes_flowsheet_processor/_testing/__init__.py
idaes_flowsheet_processor/_testing/default_tests.py
idaes_flowsheet_processor/_testing/plugins.py
idaes_flowsheet_processor/_testing/util.py
idaes_flowsheet_processor/_testing/tests/__init__.py
idaes_flowsheet_processor/_testing/tests/test_self.py
idaes_flowsheet_processor/tests/__init__.py
idaes_flowsheet_processor/tests/test_api.py
idaes_flowsheet_processor-0.2.dist-info/licenses/LICENSE.md
idaes_flowsheet_processor-0.2.dist-info/METADATA
idaes_flowsheet_processor-0.2.dist-info/WHEEL
idaes_flowsheet_processor-0.2.dist-info/entry_points.txt
idaes_flowsheet_processor-0.2.dist-info/top_level.txt
idaes_flowsheet_processor-0.2.dist-info/RECORD
