Metadata-Version: 2.4
Name: idaes-flowsheet-processor
Version: 0.2
License-File: LICENSE.md
Requires-Dist: pydantic<3,>=2
Requires-Dist: pyomo
Requires-Dist: plotly>=6.1.1
Requires-Dist: pandas>=2.2.3
Requires-Dist: numpy>=2
Requires-Dist: IPython
Provides-Extra: testing
Requires-Dist: pytest>=8; extra == "testing"
Requires-Dist: idaes-pse; extra == "testing"
Requires-Dist: watertap; extra == "testing"
Dynamic: license-file
